{"version": "5.3.0", "objects": [{"type": "image", "version": "5.3.0", "originX": "center", "originY": "center", "left": 650.3, "top": 395.5, "width": 3840, "height": 2160, "fill": "rgb(0,0,0)", "stroke": null, "strokeWidth": 0, "strokeDashArray": null, "strokeLineCap": "butt", "strokeDashOffset": 0, "strokeLineJoin": "miter", "strokeUniform": false, "strokeMiterLimit": 4, "scaleX": 0.3, "scaleY": 0.3, "angle": 0, "flipX": false, "flipY": false, "opacity": 1, "shadow": null, "visible": true, "backgroundColor": "", "fillRule": "nonzero", "paintFirst": "fill", "globalCompositeOperation": "source-over", "skewX": 0, "skewY": 0, "cropX": 0, "cropY": 0, "dataTag": "background", "selectable": true, "evented": true, "lockScalingY": false, "src": "http://truenas:5000/api/proxy/image?url=http%3A%2F%2F192.168.178.92%3A30013%2FItems%2Fa0e0696a5ab719c243d1ee980926e17a%2FImages%2FBackdrop%3Fapi_key%3Db00ae14a7c3249b2b154f22f75e1ecfd", "crossOrigin": "anonymous", "filters": []}, {"type": "rect", "version": "5.3.0", "originX": "left", "originY": "top", "left": 72.3, "top": 69.5, "width": 353, "height": 652, "fill": {"type": "linear", "coords": {"x1": 0, "y1": 0, "x2": 1, "y2": 0}, "colorStops": [{"offset": 0, "color": "#0a0907"}, {"offset": 1, "color": "rgba(10, 9, 7, 0.005)"}], "offsetX": 0, "offsetY": 0, "gradientUnits": "percentage", "gradientTransform": null}, "stroke": null, "strokeWidth": 1, "strokeDashArray": null, "strokeLineCap": "butt", "strokeDashOffset": 0, "strokeLineJoin": "miter", "strokeUniform": false, "strokeMiterLimit": 4, "scaleX": 1, "scaleY": 1, "angle": 0, "flipX": false, "flipY": false, "opacity": 1, "shadow": null, "visible": true, "backgroundColor": "", "fillRule": "nonzero", "paintFirst": "fill", "globalCompositeOperation": "source-over", "skewX": 0, "skewY": 0, "rx": 0, "ry": 0, "dataTag": "fade_effect", "selectable": false, "evented": false, "lockScalingY": false}, {"type": "rect", "version": "5.3.0", "originX": "left", "originY": "top", "left": 1023.3, "top": 69.5, "width": 205, "height": 652, "fill": {"type": "linear", "coords": {"x1": 1, "y1": 0, "x2": 0, "y2": 0}, "colorStops": [{"offset": 0, "color": "#0a0907"}, {"offset": 1, "color": "rgba(10, 9, 7, 0.005)"}], "offsetX": 0, "offsetY": 0, "gradientUnits": "percentage", "gradientTransform": null}, "stroke": null, "strokeWidth": 1, "strokeDashArray": null, "strokeLineCap": "butt", "strokeDashOffset": 0, "strokeLineJoin": "miter", "strokeUniform": false, "strokeMiterLimit": 4, "scaleX": 1, "scaleY": 1, "angle": 0, "flipX": false, "flipY": false, "opacity": 1, "shadow": null, "visible": true, "backgroundColor": "", "fillRule": "nonzero", "paintFirst": "fill", "globalCompositeOperation": "source-over", "skewX": 0, "skewY": 0, "rx": 0, "ry": 0, "dataTag": "fade_effect", "selectable": false, "evented": false, "lockScalingY": false}, {"type": "rect", "version": "5.3.0", "originX": "left", "originY": "top", "left": 72.3, "top": 69.5, "width": 1156, "height": 182, "fill": {"type": "linear", "coords": {"x1": 0, "y1": 0, "x2": 0, "y2": 1}, "colorStops": [{"offset": 0, "color": "#0a0907"}, {"offset": 1, "color": "rgba(10, 9, 7, 0.005)"}], "offsetX": 0, "offsetY": 0, "gradientUnits": "percentage", "gradientTransform": null}, "stroke": null, "strokeWidth": 1, "strokeDashArray": null, "strokeLineCap": "butt", "strokeDashOffset": 0, "strokeLineJoin": "miter", "strokeUniform": false, "strokeMiterLimit": 4, "scaleX": 1, "scaleY": 1, "angle": 0, "flipX": false, "flipY": false, "opacity": 1, "shadow": null, "visible": true, "backgroundColor": "", "fillRule": "nonzero", "paintFirst": "fill", "globalCompositeOperation": "source-over", "skewX": 0, "skewY": 0, "rx": 0, "ry": 0, "dataTag": "fade_effect", "selectable": false, "evented": false, "lockScalingY": false}, {"type": "rect", "version": "5.3.0", "originX": "left", "originY": "top", "left": 72.3, "top": 422.5, "width": 1156, "height": 299, "fill": {"type": "linear", "coords": {"x1": 0, "y1": 1, "x2": 0, "y2": 0}, "colorStops": [{"offset": 0, "color": "#0a0907"}, {"offset": 1, "color": "rgba(10, 9, 7, 0.005)"}], "offsetX": 0, "offsetY": 0, "gradientUnits": "percentage", "gradientTransform": null}, "stroke": null, "strokeWidth": 1, "strokeDashArray": null, "strokeLineCap": "butt", "strokeDashOffset": 0, "strokeLineJoin": "miter", "strokeUniform": false, "strokeMiterLimit": 4, "scaleX": 1, "scaleY": 1, "angle": 0, "flipX": false, "flipY": false, "opacity": 1, "shadow": null, "visible": true, "backgroundColor": "", "fillRule": "nonzero", "paintFirst": "fill", "globalCompositeOperation": "source-over", "skewX": 0, "skewY": 0, "rx": 0, "ry": 0, "dataTag": "fade_effect", "selectable": false, "evented": false, "lockScalingY": false}, {"type": "i-text", "version": "5.3.0", "originX": "left", "originY": "top", "left": 1391.74, "top": 412.28, "width": 67.44, "height": 33.9, "fill": "#c98282", "stroke": null, "strokeWidth": 1, "strokeDashArray": null, "strokeLineCap": "butt", "strokeDashOffset": 0, "strokeLineJoin": "miter", "strokeUniform": false, "strokeMiterLimit": 4, "scaleX": 1, "scaleY": 1, "angle": 0, "flipX": false, "flipY": false, "opacity": 1, "shadow": {"color": "rgba(0,0,0,0.8)", "blur": 10, "offsetX": 2, "offsetY": 2, "affectStroke": false, "nonScaling": false}, "visible": true, "backgroundColor": "", "fillRule": "nonzero", "paintFirst": "fill", "globalCompositeOperation": "source-over", "skewX": 0, "skewY": 0, "fontFamily": "Roboto", "fontWeight": "normal", "fontSize": 30, "text": "1986", "underline": false, "overline": false, "linethrough": false, "textAlign": "left", "fontStyle": "normal", "lineHeight": 1.16, "textBackgroundColor": "", "charSpacing": 0, "styles": [], "direction": "ltr", "path": null, "pathStartOffset": 0, "pathSide": "left", "pathAlign": "baseline", "dataTag": "year", "selectable": true, "evented": true, "lockScalingY": false, "editable": false}, {"type": "group", "version": "5.3.0", "originX": "left", "originY": "top", "left": 1480.18, "top": 412.28, "width": 112.14, "height": 34.9, "fill": "rgb(0,0,0)", "stroke": null, "strokeWidth": 0, "strokeDashArray": null, "strokeLineCap": "butt", "strokeDashOffset": 0, "strokeLineJoin": "miter", "strokeUniform": false, "strokeMiterLimit": 4, "scaleX": 1, "scaleY": 1, "angle": 0, "flipX": false, "flipY": false, "opacity": 1, "shadow": null, "visible": true, "backgroundColor": "", "fillRule": "nonzero", "paintFirst": "fill", "globalCompositeOperation": "source-over", "skewX": 0, "skewY": 0, "dataTag": "rating", "selectable": true, "evented": true, "lockScalingY": false, "objects": [{"type": "image", "version": "5.3.0", "originX": "left", "originY": "top", "left": -56.07, "top": -15, "width": 1200, "height": 605, "fill": "rgb(0,0,0)", "stroke": null, "strokeWidth": 0, "strokeDashArray": null, "strokeLineCap": "butt", "strokeDashOffset": 0, "strokeLineJoin": "miter", "strokeUniform": false, "strokeMiterLimit": 4, "scaleX": 0.05, "scaleY": 0.05, "angle": 0, "flipX": false, "flipY": false, "opacity": 1, "shadow": null, "visible": true, "backgroundColor": "", "fillRule": "nonzero", "paintFirst": "fill", "globalCompositeOperation": "source-over", "skewX": 0, "skewY": 0, "cropX": 0, "cropY": 0, "dataTag": "rating_logo_img", "selectable": true, "evented": true, "lockScalingY": false, "src": "http://truenas:5000/api/proxy/image?url=https%3A%2F%2Fupload.wikimedia.org%2Fwikipedia%2Fcommons%2Fthumb%2F6%2F69%2FIMDB_Logo_2016.svg%2F1200px-IMDB_Logo_2016.svg.png", "crossOrigin": "anonymous", "filters": []}, {"type": "i-text", "version": "5.3.0", "originX": "left", "originY": "top", "left": 13.44, "top": -17.45, "width": 41.63, "height": 33.9, "fill": "#c98282", "stroke": null, "strokeWidth": 1, "strokeDashArray": null, "strokeLineCap": "butt", "strokeDashOffset": 0, "strokeLineJoin": "miter", "strokeUniform": false, "strokeMiterLimit": 4, "scaleX": 1, "scaleY": 1, "angle": 0, "flipX": false, "flipY": false, "opacity": 1, "shadow": null, "visible": true, "backgroundColor": "", "fillRule": "nonzero", "paintFirst": "fill", "globalCompositeOperation": "source-over", "skewX": 0, "skewY": 0, "fontFamily": "Roboto", "fontWeight": "normal", "fontSize": 30, "text": "6.3", "underline": false, "overline": false, "linethrough": false, "textAlign": "left", "fontStyle": "normal", "lineHeight": 1.16, "textBackgroundColor": "", "charSpacing": 0, "styles": [], "direction": "ltr", "path": null, "pathStartOffset": 0, "pathSide": "left", "pathAlign": "baseline", "dataTag": "rating", "selectable": true, "evented": true, "lockScalingY": false, "editable": false}]}, {"type": "i-text", "version": "5.3.0", "originX": "left", "originY": "top", "left": 1667.22, "top": 412.28, "width": 86.06, "height": 33.9, "fill": "#c98282", "stroke": null, "strokeWidth": 1, "strokeDashArray": null, "strokeLineCap": "butt", "strokeDashOffset": 0, "strokeLineJoin": "miter", "strokeUniform": false, "strokeMiterLimit": 4, "scaleX": 1, "scaleY": 1, "angle": 0, "flipX": false, "flipY": false, "opacity": 1, "shadow": {"color": "rgba(0,0,0,0.8)", "blur": 10, "offsetX": 2, "offsetY": 2, "affectStroke": false, "nonScaling": false}, "visible": true, "backgroundColor": "", "fillRule": "nonzero", "paintFirst": "fill", "globalCompositeOperation": "source-over", "skewX": 0, "skewY": 0, "fontFamily": "Roboto", "fontWeight": "normal", "fontSize": 30, "text": "Action", "underline": false, "overline": false, "linethrough": false, "textAlign": "left", "fontStyle": "normal", "lineHeight": 1.16, "textBackgroundColor": "", "charSpacing": 0, "styles": [], "direction": "ltr", "path": null, "pathStartOffset": 0, "pathSide": "left", "pathAlign": "baseline", "dataTag": "genres", "selectable": true, "evented": true, "lockScalingY": false, "editable": false}, {"type": "i-text", "version": "5.3.0", "originX": "left", "originY": "top", "left": 1774.28, "top": 412.28, "width": 124.72, "height": 33.9, "fill": "#c98282", "stroke": null, "strokeWidth": 1, "strokeDashArray": null, "strokeLineCap": "butt", "strokeDashOffset": 0, "strokeLineJoin": "miter", "strokeUniform": false, "strokeMiterLimit": 4, "scaleX": 1, "scaleY": 1, "angle": 0, "flipX": false, "flipY": false, "opacity": 1, "shadow": {"color": "rgba(0,0,0,0.8)", "blur": 10, "offsetX": 2, "offsetY": 2, "affectStroke": false, "nonScaling": false}, "visible": true, "backgroundColor": "", "fillRule": "nonzero", "paintFirst": "fill", "globalCompositeOperation": "source-over", "skewX": 0, "skewY": 0, "fontFamily": "Roboto", "fontWeight": "normal", "fontSize": 30, "text": "1h 39min", "underline": false, "overline": false, "linethrough": false, "textAlign": "left", "fontStyle": "normal", "lineHeight": 1.16, "textBackgroundColor": "", "charSpacing": 0, "styles": [], "direction": "ltr", "path": null, "pathStartOffset": 0, "pathSide": "left", "pathAlign": "baseline", "dataTag": "runtime", "selectable": true, "evented": true, "lockScalingY": false, "editable": false}, {"type": "textbox", "version": "5.3.0", "originX": "left", "originY": "top", "left": 1299, "top": 467.18, "width": 600, "height": 83.05, "fill": "white", "stroke": null, "strokeWidth": 1, "strokeDashArray": null, "strokeLineCap": "butt", "strokeDashOffset": 0, "strokeLineJoin": "miter", "strokeUniform": false, "strokeMiterLimit": 4, "scaleX": 1, "scaleY": 1, "angle": 0, "flipX": false, "flipY": false, "opacity": 1, "shadow": {"color": "rgba(0,0,0,0.8)", "blur": 10, "offsetX": 2, "offsetY": 2, "affectStroke": false, "nonScaling": false}, "visible": true, "backgroundColor": "", "fillRule": "nonzero", "paintFirst": "fill", "globalCompositeOperation": "source-over", "skewX": 0, "skewY": 0, "fontFamily": "Roboto", "fontWeight": "normal", "fontSize": 35, "text": "Von einem skrupellosen Verbrecher-Syndikat unter Druck...", "underline": false, "overline": false, "linethrough": false, "textAlign": "right", "fontStyle": "normal", "lineHeight": 1.1, "textBackgroundColor": "", "charSpacing": 0, "styles": [], "direction": "ltr", "path": null, "pathStartOffset": 0, "pathSide": "left", "pathAlign": "baseline", "minWidth": 20, "splitByGrapheme": false, "dataTag": "overview", "fullMediaText": "Von einem skrupellosen Verbrecher-Syndikat unter Druck gesetzt, zieht es der Karatelehrer Stillwell vor, Los Angeles zu verlassen, um sich in Seattle eine neue Existenz aufzubauen. Sein Sohn Jason, ein gl\u00fchender Verehrer von Bruce Lee, dessen Kampftechnik und Philosophie ihn fasziniert, ist \u00fcber das feige Verhalten seines Vaters tief entt\u00e4uscht. Niedergeschlagen und verzweifelt pilgert Jason in Seattle, der Heimatstadt Lee's, zu dessen Grab und fleht ihn um Beistand an. Von nun an trainiert Jason wie ein Besessener. Er will seine Kampftechnik ganz im Stil seines gro\u00dfen Vorbildes perfektionieren. Eines Nachts erscheint ihm der Meister im Traum und lehrt ihn alle Geheimnisse seines Erfolges. Gewappnet mit kostbarem Wissen und st\u00e4hlernem Mut, nimmt Jason den Kampf gegen die kriminellen Elemente der Stadt auf. Erst als er die Herausforderung erh\u00e4lt, gegen den Russen Ivan zu k\u00e4mpfen, kommt Jason in gro\u00dfe Bedr\u00e4ngnis. Es ist eine Herausforderung auf Leben und Tod...", "selectable": true, "evented": true, "lockScalingY": false, "fixedHeight": 130.4889557855129, "editable": false}, {"type": "i-text", "version": "5.3.0", "originX": "left", "originY": "top", "left": 1569.63, "top": 571.24, "width": 329.37, "height": 33.9, "fill": "#c98282", "stroke": null, "strokeWidth": 1, "strokeDashArray": null, "strokeLineCap": "butt", "strokeDashOffset": 0, "strokeLineJoin": "miter", "strokeUniform": false, "strokeMiterLimit": 4, "scaleX": 1, "scaleY": 1, "angle": 0, "flipX": false, "flipY": false, "opacity": 1, "shadow": {"color": "rgba(0,0,0,0.8)", "blur": 10, "offsetX": 2, "offsetY": 2, "affectStroke": false, "nonScaling": false}, "visible": true, "backgroundColor": "", "fillRule": "nonzero", "paintFirst": "fill", "globalCompositeOperation": "source-over", "skewX": 0, "skewY": 0, "fontFamily": "Roboto", "fontWeight": "normal", "fontSize": 30, "text": "Now available on Jellyfin", "underline": false, "overline": false, "linethrough": false, "textAlign": "right", "fontStyle": "normal", "lineHeight": 1.16, "textBackgroundColor": "", "charSpacing": 0, "styles": [], "direction": "ltr", "path": null, "pathStartOffset": 0, "pathSide": "left", "pathAlign": "baseline", "dataTag": "provider_source", "selectable": true, "evented": true, "lockScalingY": false, "editable": false}, {"type": "image", "version": "5.3.0", "originX": "left", "originY": "top", "left": 0, "top": 0, "width": 1920, "height": 1080, "fill": "rgb(0,0,0)", "stroke": null, "strokeWidth": 0, "strokeDashArray": null, "strokeLineCap": "butt", "strokeDashOffset": 0, "strokeLineJoin": "miter", "strokeUniform": false, "strokeMiterLimit": 4, "scaleX": 1, "scaleY": 1, "angle": 0, "flipX": false, "flipY": false, "opacity": 0.5, "shadow": null, "visible": true, "backgroundColor": "", "fillRule": "nonzero", "paintFirst": "fill", "globalCompositeOperation": "source-over", "skewX": 0, "skewY": 0, "cropX": 0, "cropY": 0, "dataTag": "guide_overlay", "selectable": false, "evented": false, "lockScalingY": false, "src": "http://truenas:5000/api/overlays/image/ec26c288-c32c-4da2-a395-99a7e507f950_1080.png", "crossOrigin": null, "filters": []}, {"type": "image", "version": "5.3.0", "originX": "left", "originY": "top", "left": 951.14, "top": 161, "width": 800, "height": 195, "fill": "rgb(0,0,0)", "stroke": null, "strokeWidth": 0, "strokeDashArray": null, "strokeLineCap": "butt", "strokeDashOffset": 0, "strokeLineJoin": "miter", "strokeUniform": false, "strokeMiterLimit": 4, "scaleX": 1.19, "scaleY": 1.19, "angle": 0, "flipX": false, "flipY": false, "opacity": 1, "shadow": null, "visible": true, "backgroundColor": "", "fillRule": "nonzero", "paintFirst": "fill", "globalCompositeOperation": "source-over", "skewX": 0, "skewY": 0, "cropX": 0, "cropY": 0, "dataTag": "title", "selectable": true, "evented": true, "lockScalingY": false, "src": "http://truenas:5000/api/proxy/image?url=http%3A%2F%2F192.168.178.92%3A30013%2FItems%2Fa0e0696a5ab719c243d1ee980926e17a%2FImages%2FLogo%3Fapi_key%3Db00ae14a7c3249b2b154f22f75e1ecfd&raw=true", "crossOrigin": "anonymous", "filters": []}, {"type": "image", "version": "5.3.0", "originX": "left", "originY": "top", "left": 1612.32, "top": 412.28, "width": 768, "height": 768, "fill": "rgb(0,0,0)", "stroke": null, "strokeWidth": 0, "strokeDashArray": null, "strokeLineCap": "butt", "strokeDashOffset": 0, "strokeLineJoin": "miter", "strokeUniform": false, "strokeMiterLimit": 4, "scaleX": 0.05, "scaleY": 0.05, "angle": 0, "flipX": false, "flipY": false, "opacity": 1, "shadow": null, "visible": true, "backgroundColor": "", "fillRule": "nonzero", "paintFirst": "fill", "globalCompositeOperation": "source-over", "skewX": 0, "skewY": 0, "cropX": 0, "cropY": 0, "dataTag": "certification", "selectable": true, "evented": true, "lockScalingY": false, "matchHeight": true, "src": "http://truenas:5000/api/certification/FSK_16.svg", "crossOrigin": "anonymous", "filters": []}], "background": "#0a0907", "metadata": {"title": "Karate Tiger", "year": 1986, "officialRating": "FSK-16", "communityRating": 6.3, "genres": "Action, Kom\u00f6die, Krimi, Drama", "overview": "Von einem skrupellosen Verbrecher-Syndikat unter Druck gesetzt, zieht es der Karatelehrer Stillwell vor, Los Angeles zu verlassen, um sich in Seattle eine neue Existenz aufzubauen. Sein Sohn Jason, ein gl\u00fchender Verehrer von Bruce Lee, dessen Kampftechnik und Philosophie ihn fasziniert, ist \u00fcber das feige Verhalten seines Vaters tief entt\u00e4uscht. Niedergeschlagen und verzweifelt pilgert Jason in Seattle, der Heimatstadt Lee's, zu dessen Grab und fleht ihn um Beistand an. Von nun an trainiert Jason wie ein Besessener. Er will seine Kampftechnik ganz im Stil seines gro\u00dfen Vorbildes perfektionieren. Eines Nachts erscheint ihm der Meister im Traum und lehrt ihn alle Geheimnisse seines Erfolges. Gewappnet mit kostbarem Wissen und st\u00e4hlernem Mut, nimmt Jason den Kampf gegen die kriminellen Elemente der Stadt auf. Erst als er die Herausforderung erh\u00e4lt, gegen den Russen Ivan zu k\u00e4mpfen, kommt Jason in gro\u00dfe Bedr\u00e4ngnis. Es ist eine Herausforderung auf Leben und Tod...", "action_url": "jellyfin://items/a0e0696a5ab719c243d1ee980926e17a", "provider_ids": {"Imdb": "tt0089695", "Tmdb": "12721", "TmdbCollection": "384920", "tmdbSet": "384920", "wikidata": "Q1326650"}, "studios": [], "tags": [], "source": "Jellyfin"}, "action_url": "jellyfin://items/a0e0696a5ab719c243d1ee980926e17a"}