{"version": "5.3.0", "objects": [{"type": "image", "version": "5.3.0", "originX": "left", "originY": "top", "left": 576, "top": 0, "width": 2500, "height": 1406, "fill": "rgb(0,0,0)", "stroke": null, "strokeWidth": 0, "strokeDashArray": null, "strokeLineCap": "butt", "strokeDashOffset": 0, "strokeLineJoin": "miter", "strokeUniform": false, "strokeMiterLimit": 4, "scaleX": 0.54, "scaleY": 0.54, "angle": 0, "flipX": false, "flipY": false, "opacity": 1, "shadow": null, "visible": true, "backgroundColor": "", "fillRule": "nonzero", "paintFirst": "fill", "globalCompositeOperation": "source-over", "skewX": 0, "skewY": 0, "cropX": 0, "cropY": 0, "dataTag": "background", "selectable": true, "evented": true, "lockScalingY": false, "src": "http://127.0.0.1:5000/api/proxy/image?url=http%3A%2F%2Ftruenas%3A30013%2FItems%2F11ff5787dc8d413167bed74d829ee244%2FImages%2FBackdrop%3Fapi_key%3Db00ae14a7c3249b2b154f22f75e1ecfd", "crossOrigin": "anonymous", "filters": []}, {"type": "rect", "version": "5.3.0", "originX": "left", "originY": "top", "left": 574, "top": 435.87, "width": 1348, "height": 322, "fill": {"type": "linear", "coords": {"x1": 0, "y1": 1, "x2": 0, "y2": 0}, "colorStops": [{"offset": 0, "color": "#030302"}, {"offset": 1, "color": "rgba(3, 3, 2, 0.005)"}], "offsetX": 0, "offsetY": 0, "gradientUnits": "percentage", "gradientTransform": null}, "stroke": null, "strokeWidth": 1, "strokeDashArray": null, "strokeLineCap": "butt", "strokeDashOffset": 0, "strokeLineJoin": "miter", "strokeUniform": false, "strokeMiterLimit": 4, "scaleX": 1, "scaleY": 1, "angle": 0, "flipX": false, "flipY": false, "opacity": 1, "shadow": null, "visible": true, "backgroundColor": "", "fillRule": "nonzero", "paintFirst": "fill", "globalCompositeOperation": "source-over", "skewX": 0, "skewY": 0, "rx": 0, "ry": 0, "dataTag": "fade_effect", "selectable": false, "evented": false, "lockScalingY": false}, {"type": "rect", "version": "5.3.0", "originX": "left", "originY": "top", "left": 574, "top": -2, "width": 582, "height": 759.87, "fill": {"type": "linear", "coords": {"x1": 0, "y1": 0, "x2": 1, "y2": 0}, "colorStops": [{"offset": 0, "color": "#030302"}, {"offset": 1, "color": "rgba(3, 3, 2, 0.005)"}], "offsetX": 0, "offsetY": 0, "gradientUnits": "percentage", "gradientTransform": null}, "stroke": null, "strokeWidth": 1, "strokeDashArray": null, "strokeLineCap": "butt", "strokeDashOffset": 0, "strokeLineJoin": "miter", "strokeUniform": false, "strokeMiterLimit": 4, "scaleX": 1, "scaleY": 1, "angle": 0, "flipX": false, "flipY": false, "opacity": 1, "shadow": null, "visible": true, "backgroundColor": "", "fillRule": "nonzero", "paintFirst": "fill", "globalCompositeOperation": "source-over", "skewX": 0, "skewY": 0, "rx": 0, "ry": 0, "dataTag": "fade_effect", "selectable": false, "evented": false, "lockScalingY": false}, {"type": "i-text", "version": "5.3.0", "originX": "left", "originY": "top", "left": 855.92, "top": 169.5, "width": 66.46, "height": 39.55, "fill": "#c14e4e", "stroke": null, "strokeWidth": 1, "strokeDashArray": null, "strokeLineCap": "butt", "strokeDashOffset": 0, "strokeLineJoin": "miter", "strokeUniform": false, "strokeMiterLimit": 4, "scaleX": 1, "scaleY": 1, "angle": 0, "flipX": false, "flipY": false, "opacity": 1, "shadow": {"color": "rgba(0,0,0,0.8)", "blur": 10, "offsetX": 2, "offsetY": 2, "affectStroke": false, "nonScaling": false}, "visible": true, "backgroundColor": "", "fillRule": "nonzero", "paintFirst": "fill", "globalCompositeOperation": "source-over", "skewX": 0, "skewY": 0, "fontFamily": "Oswald", "fontWeight": "normal", "fontSize": 35, "text": "1990", "underline": false, "overline": false, "linethrough": false, "textAlign": "left", "fontStyle": "normal", "lineHeight": 1.16, "textBackgroundColor": "", "charSpacing": 0, "styles": [], "direction": "ltr", "path": null, "pathStartOffset": 0, "pathSide": "left", "pathAlign": "baseline", "dataTag": "year", "selectable": true, "evented": true, "lockScalingY": false, "editable": false}, {"type": "i-text", "version": "5.3.0", "originX": "left", "originY": "top", "left": 753.55, "top": 169.5, "width": 81.37, "height": 39.55, "fill": "#c14e4e", "stroke": null, "strokeWidth": 1, "strokeDashArray": null, "strokeLineCap": "butt", "strokeDashOffset": 0, "strokeLineJoin": "miter", "strokeUniform": false, "strokeMiterLimit": 4, "scaleX": 1, "scaleY": 1, "angle": 0, "flipX": false, "flipY": false, "opacity": 1, "shadow": {"color": "rgba(0,0,0,0.8)", "blur": 10, "offsetX": 2, "offsetY": 2, "affectStroke": false, "nonScaling": false}, "visible": true, "backgroundColor": "", "fillRule": "nonzero", "paintFirst": "fill", "globalCompositeOperation": "source-over", "skewX": 0, "skewY": 0, "fontFamily": "Oswald", "fontWeight": "normal", "fontSize": 35, "text": "Drama", "underline": false, "overline": false, "linethrough": false, "textAlign": "left", "fontStyle": "normal", "lineHeight": 1.16, "textBackgroundColor": "", "charSpacing": 0, "styles": [], "direction": "ltr", "path": null, "pathStartOffset": 0, "pathSide": "left", "pathAlign": "baseline", "dataTag": "genres", "selectable": true, "evented": true, "lockScalingY": false, "editable": false}, {"type": "i-text", "version": "5.3.0", "originX": "left", "originY": "top", "left": 615.34, "top": 169.5, "width": 117.21, "height": 39.55, "fill": "#c14e4e", "stroke": null, "strokeWidth": 1, "strokeDashArray": null, "strokeLineCap": "butt", "strokeDashOffset": 0, "strokeLineJoin": "miter", "strokeUniform": false, "strokeMiterLimit": 4, "scaleX": 1, "scaleY": 1, "angle": 0, "flipX": false, "flipY": false, "opacity": 1, "shadow": {"color": "rgba(0,0,0,0.8)", "blur": 10, "offsetX": 2, "offsetY": 2, "affectStroke": false, "nonScaling": false}, "visible": true, "backgroundColor": "", "fillRule": "nonzero", "paintFirst": "fill", "globalCompositeOperation": "source-over", "skewX": 0, "skewY": 0, "fontFamily": "Oswald", "fontWeight": "normal", "fontSize": 35, "text": "2h 14min", "underline": false, "overline": false, "linethrough": false, "textAlign": "left", "fontStyle": "normal", "lineHeight": 1.16, "textBackgroundColor": "", "charSpacing": 0, "styles": [], "direction": "ltr", "path": null, "pathStartOffset": 0, "pathSide": "left", "pathAlign": "baseline", "dataTag": "runtime", "selectable": true, "evented": true, "lockScalingY": false, "editable": false}, {"type": "image", "version": "5.3.0", "originX": "left", "originY": "top", "left": 391.71, "top": 169.5, "width": 1200, "height": 605, "fill": "rgb(0,0,0)", "stroke": null, "strokeWidth": 0, "strokeDashArray": null, "strokeLineCap": "butt", "strokeDashOffset": 0, "strokeLineJoin": "miter", "strokeUniform": false, "strokeMiterLimit": 4, "scaleX": 0.07, "scaleY": 0.07, "angle": 0, "flipX": false, "flipY": false, "opacity": 1, "shadow": null, "visible": true, "backgroundColor": "", "fillRule": "nonzero", "paintFirst": "fill", "globalCompositeOperation": "source-over", "skewX": 0, "skewY": 0, "cropX": 0, "cropY": 0, "dataTag": "icon", "selectable": true, "evented": true, "lockScalingY": false, "matchHeight": true, "src": "http://127.0.0.1:5000/api/proxy/image?url=https%3A%2F%2Fupload.wikimedia.org%2Fwikipedia%2Fcommons%2Fthumb%2F6%2F69%2FIMDB_Logo_2016.svg%2F1200px-IMDB_Logo_2016.svg.png", "crossOrigin": "anonymous", "filters": []}, {"type": "image", "version": "5.3.0", "originX": "left", "originY": "top", "left": 554.79, "top": 169.5, "width": 768, "height": 768, "fill": "rgb(0,0,0)", "stroke": null, "strokeWidth": 0, "strokeDashArray": null, "strokeLineCap": "butt", "strokeDashOffset": 0, "strokeLineJoin": "miter", "strokeUniform": false, "strokeMiterLimit": 4, "scaleX": 0.05, "scaleY": 0.05, "angle": 0, "flipX": false, "flipY": false, "opacity": 1, "shadow": null, "visible": true, "backgroundColor": "", "fillRule": "nonzero", "paintFirst": "fill", "globalCompositeOperation": "source-over", "skewX": 0, "skewY": 0, "cropX": 0, "cropY": 0, "dataTag": "certification", "selectable": true, "evented": true, "lockScalingY": false, "matchHeight": true, "src": "http://127.0.0.1:5000/api/certification/FSK_16.svg", "crossOrigin": "anonymous", "filters": []}, {"type": "i-text", "version": "5.3.0", "originX": "left", "originY": "top", "left": 492.14, "top": 169.5, "width": 41.65, "height": 39.55, "fill": "#c14e4e", "stroke": null, "strokeWidth": 1, "strokeDashArray": null, "strokeLineCap": "butt", "strokeDashOffset": 0, "strokeLineJoin": "miter", "strokeUniform": false, "strokeMiterLimit": 4, "scaleX": 1, "scaleY": 1, "angle": 0, "flipX": false, "flipY": false, "opacity": 1, "shadow": {"color": "rgba(0,0,0,0.8)", "blur": 10, "offsetX": 2, "offsetY": 2, "affectStroke": false, "nonScaling": false}, "visible": true, "backgroundColor": "", "fillRule": "nonzero", "paintFirst": "fill", "globalCompositeOperation": "source-over", "skewX": 0, "skewY": 0, "fontFamily": "Oswald", "fontWeight": "normal", "fontSize": 35, "text": "6.9", "underline": false, "overline": false, "linethrough": false, "textAlign": "left", "fontStyle": "normal", "lineHeight": 1.16, "textBackgroundColor": "", "charSpacing": 0, "styles": [], "direction": "ltr", "path": null, "pathStartOffset": 0, "pathSide": "left", "pathAlign": "baseline", "dataTag": "rating_val", "selectable": true, "evented": true, "lockScalingY": false, "editable": false}, {"type": "textbox", "version": "5.3.0", "originX": "left", "originY": "top", "left": 357.05, "top": 230.05, "width": 600, "height": 223.06, "fill": "white", "stroke": null, "strokeWidth": 1, "strokeDashArray": null, "strokeLineCap": "butt", "strokeDashOffset": 0, "strokeLineJoin": "miter", "strokeUniform": false, "strokeMiterLimit": 4, "scaleX": 1, "scaleY": 1, "angle": 0, "flipX": false, "flipY": false, "opacity": 1, "shadow": {"color": "rgba(0,0,0,0.8)", "blur": 10, "offsetX": 2, "offsetY": 2, "affectStroke": false, "nonScaling": false}, "visible": true, "backgroundColor": "", "fillRule": "nonzero", "paintFirst": "fill", "globalCompositeOperation": "source-over", "skewX": 0, "skewY": 0, "fontFamily": "Oswald", "fontWeight": "normal", "fontSize": 35, "text": "Hell's Kitchen, New York. Terry Noonan kehrt nach zehnj\u00e4hriger Abwesenheit nach Hause zur\u00fcck. Schon bald trifft er Jackie, einen Freund aus Kindertagen und Mitglied der irischen Mafia,...", "underline": false, "overline": false, "linethrough": false, "textAlign": "center", "fontStyle": "normal", "lineHeight": 1.16, "textBackgroundColor": "", "charSpacing": 0, "styles": [], "direction": "ltr", "path": null, "pathStartOffset": 0, "pathSide": "left", "pathAlign": "baseline", "minWidth": 20, "splitByGrapheme": false, "dataTag": "overview", "fullMediaText": "Hell's Kitchen, New York. Terry Noonan kehrt nach zehnj\u00e4hriger Abwesenheit nach Hause zur\u00fcck. Schon bald trifft er Jackie, einen Freund aus Kindertagen und Mitglied der irischen Mafia, wieder und entfacht seine Liebesbeziehung zu Jackies Schwester Kathleen neu.", "selectable": true, "evented": true, "lockScalingY": false, "fixedHeight": 300, "editable": false}, {"type": "i-text", "version": "5.3.0", "originX": "left", "originY": "top", "left": 476.75, "top": 474.11, "width": 360.6, "height": 39.55, "fill": "#c14e4e", "stroke": null, "strokeWidth": 1, "strokeDashArray": null, "strokeLineCap": "butt", "strokeDashOffset": 0, "strokeLineJoin": "miter", "strokeUniform": false, "strokeMiterLimit": 4, "scaleX": 1, "scaleY": 1, "angle": 0, "flipX": false, "flipY": false, "opacity": 1, "shadow": {"color": "rgba(0,0,0,0.8)", "blur": 10, "offsetX": 2, "offsetY": 2, "affectStroke": false, "nonScaling": false}, "visible": true, "backgroundColor": "", "fillRule": "nonzero", "paintFirst": "fill", "globalCompositeOperation": "source-over", "skewX": 0, "skewY": 0, "fontFamily": "Oswald", "fontWeight": "normal", "fontSize": 35, "text": "Now available on Jellyfin", "underline": false, "overline": false, "linethrough": false, "textAlign": "left", "fontStyle": "normal", "lineHeight": 1.16, "textBackgroundColor": "", "charSpacing": 0, "styles": [], "direction": "ltr", "path": null, "pathStartOffset": 0, "pathSide": "left", "pathAlign": "baseline", "dataTag": "provider_source", "selectable": true, "evented": true, "lockScalingY": false, "editable": false}, {"type": "image", "version": "5.3.0", "originX": "left", "originY": "top", "left": 235.15, "top": 50, "width": 2632, "height": 310, "fill": "rgb(0,0,0)", "stroke": null, "strokeWidth": 0, "strokeDashArray": null, "strokeLineCap": "butt", "strokeDashOffset": 0, "strokeLineJoin": "miter", "strokeUniform": false, "strokeMiterLimit": 4, "scaleX": 0.32, "scaleY": 0.32, "angle": 0, "flipX": false, "flipY": false, "opacity": 1, "shadow": null, "visible": true, "backgroundColor": "", "fillRule": "nonzero", "paintFirst": "fill", "globalCompositeOperation": "source-over", "skewX": 0, "skewY": 0, "cropX": 0, "cropY": 0, "dataTag": "title", "selectable": true, "evented": true, "lockScalingY": false, "src": "http://127.0.0.1:5000/api/proxy/image?url=http%3A%2F%2Ftruenas%3A30013%2FItems%2F11ff5787dc8d413167bed74d829ee244%2FImages%2FLogo%3Fapi_key%3Db00ae14a7c3249b2b154f22f75e1ecfd", "crossOrigin": "anonymous", "filters": []}], "background": "#030302"}