{"version": "5.3.0", "objects": [{"type": "image", "version": "5.3.0", "originX": "center", "originY": "center", "left": 650.3, "top": 395.5, "width": 3840, "height": 2160, "fill": "rgb(0,0,0)", "stroke": null, "strokeWidth": 0, "strokeDashArray": null, "strokeLineCap": "butt", "strokeDashOffset": 0, "strokeLineJoin": "miter", "strokeUniform": false, "strokeMiterLimit": 4, "scaleX": 0.3, "scaleY": 0.3, "angle": 0, "flipX": false, "flipY": false, "opacity": 1, "shadow": null, "visible": true, "backgroundColor": "", "fillRule": "nonzero", "paintFirst": "fill", "globalCompositeOperation": "source-over", "skewX": 0, "skewY": 0, "cropX": 0, "cropY": 0, "dataTag": "background", "selectable": true, "evented": true, "lockScalingY": false, "src": "http://truenas:5000/api/proxy/image?url=http%3A%2F%2F192.168.178.92%3A30013%2FItems%2Fef573e398247f1814684eb9e637ab615%2FImages%2FBackdrop%3Fapi_key%3Db00ae14a7c3249b2b154f22f75e1ecfd", "crossOrigin": "anonymous", "filters": []}, {"type": "rect", "version": "5.3.0", "originX": "left", "originY": "top", "left": 72.3, "top": 69.5, "width": 353, "height": 652, "fill": {"type": "linear", "coords": {"x1": 0, "y1": 0, "x2": 1, "y2": 0}, "colorStops": [{"offset": 0, "color": "#1c1c1c"}, {"offset": 1, "color": "rgba(28, 28, 28, 0.005)"}], "offsetX": 0, "offsetY": 0, "gradientUnits": "percentage", "gradientTransform": null}, "stroke": null, "strokeWidth": 1, "strokeDashArray": null, "strokeLineCap": "butt", "strokeDashOffset": 0, "strokeLineJoin": "miter", "strokeUniform": false, "strokeMiterLimit": 4, "scaleX": 1, "scaleY": 1, "angle": 0, "flipX": false, "flipY": false, "opacity": 1, "shadow": null, "visible": true, "backgroundColor": "", "fillRule": "nonzero", "paintFirst": "fill", "globalCompositeOperation": "source-over", "skewX": 0, "skewY": 0, "rx": 0, "ry": 0, "dataTag": "fade_effect", "selectable": false, "evented": false, "lockScalingY": false}, {"type": "rect", "version": "5.3.0", "originX": "left", "originY": "top", "left": 1023.3, "top": 69.5, "width": 205, "height": 652, "fill": {"type": "linear", "coords": {"x1": 1, "y1": 0, "x2": 0, "y2": 0}, "colorStops": [{"offset": 0, "color": "#1c1c1c"}, {"offset": 1, "color": "rgba(28, 28, 28, 0.005)"}], "offsetX": 0, "offsetY": 0, "gradientUnits": "percentage", "gradientTransform": null}, "stroke": null, "strokeWidth": 1, "strokeDashArray": null, "strokeLineCap": "butt", "strokeDashOffset": 0, "strokeLineJoin": "miter", "strokeUniform": false, "strokeMiterLimit": 4, "scaleX": 1, "scaleY": 1, "angle": 0, "flipX": false, "flipY": false, "opacity": 1, "shadow": null, "visible": true, "backgroundColor": "", "fillRule": "nonzero", "paintFirst": "fill", "globalCompositeOperation": "source-over", "skewX": 0, "skewY": 0, "rx": 0, "ry": 0, "dataTag": "fade_effect", "selectable": false, "evented": false, "lockScalingY": false}, {"type": "rect", "version": "5.3.0", "originX": "left", "originY": "top", "left": 72.3, "top": 69.5, "width": 1156, "height": 182, "fill": {"type": "linear", "coords": {"x1": 0, "y1": 0, "x2": 0, "y2": 1}, "colorStops": [{"offset": 0, "color": "#1c1c1c"}, {"offset": 1, "color": "rgba(28, 28, 28, 0.005)"}], "offsetX": 0, "offsetY": 0, "gradientUnits": "percentage", "gradientTransform": null}, "stroke": null, "strokeWidth": 1, "strokeDashArray": null, "strokeLineCap": "butt", "strokeDashOffset": 0, "strokeLineJoin": "miter", "strokeUniform": false, "strokeMiterLimit": 4, "scaleX": 1, "scaleY": 1, "angle": 0, "flipX": false, "flipY": false, "opacity": 1, "shadow": null, "visible": true, "backgroundColor": "", "fillRule": "nonzero", "paintFirst": "fill", "globalCompositeOperation": "source-over", "skewX": 0, "skewY": 0, "rx": 0, "ry": 0, "dataTag": "fade_effect", "selectable": false, "evented": false, "lockScalingY": false}, {"type": "rect", "version": "5.3.0", "originX": "left", "originY": "top", "left": 72.3, "top": 422.5, "width": 1156, "height": 299, "fill": {"type": "linear", "coords": {"x1": 0, "y1": 1, "x2": 0, "y2": 0}, "colorStops": [{"offset": 0, "color": "#1c1c1c"}, {"offset": 1, "color": "rgba(28, 28, 28, 0.005)"}], "offsetX": 0, "offsetY": 0, "gradientUnits": "percentage", "gradientTransform": null}, "stroke": null, "strokeWidth": 1, "strokeDashArray": null, "strokeLineCap": "butt", "strokeDashOffset": 0, "strokeLineJoin": "miter", "strokeUniform": false, "strokeMiterLimit": 4, "scaleX": 1, "scaleY": 1, "angle": 0, "flipX": false, "flipY": false, "opacity": 1, "shadow": null, "visible": true, "backgroundColor": "", "fillRule": "nonzero", "paintFirst": "fill", "globalCompositeOperation": "source-over", "skewX": 0, "skewY": 0, "rx": 0, "ry": 0, "dataTag": "fade_effect", "selectable": false, "evented": false, "lockScalingY": false}, {"type": "i-text", "version": "5.3.0", "originX": "left", "originY": "top", "left": 1389.59, "top": 492.14, "width": 67.44, "height": 33.9, "fill": "#c98282", "stroke": null, "strokeWidth": 1, "strokeDashArray": null, "strokeLineCap": "butt", "strokeDashOffset": 0, "strokeLineJoin": "miter", "strokeUniform": false, "strokeMiterLimit": 4, "scaleX": 1, "scaleY": 1, "angle": 0, "flipX": false, "flipY": false, "opacity": 1, "shadow": {"color": "rgba(0,0,0,0.8)", "blur": 10, "offsetX": 2, "offsetY": 2, "affectStroke": false, "nonScaling": false}, "visible": true, "backgroundColor": "", "fillRule": "nonzero", "paintFirst": "fill", "globalCompositeOperation": "source-over", "skewX": 0, "skewY": 0, "fontFamily": "Roboto", "fontWeight": "normal", "fontSize": 30, "text": "2015", "underline": false, "overline": false, "linethrough": false, "textAlign": "left", "fontStyle": "normal", "lineHeight": 1.16, "textBackgroundColor": "", "charSpacing": 0, "styles": [], "direction": "ltr", "path": null, "pathStartOffset": 0, "pathSide": "left", "pathAlign": "baseline", "dataTag": "year", "selectable": true, "evented": true, "lockScalingY": false, "editable": false}, {"type": "group", "version": "5.3.0", "originX": "left", "originY": "top", "left": 1478.03, "top": 492.14, "width": 112.14, "height": 34.9, "fill": "rgb(0,0,0)", "stroke": null, "strokeWidth": 0, "strokeDashArray": null, "strokeLineCap": "butt", "strokeDashOffset": 0, "strokeLineJoin": "miter", "strokeUniform": false, "strokeMiterLimit": 4, "scaleX": 1, "scaleY": 1, "angle": 0, "flipX": false, "flipY": false, "opacity": 1, "shadow": null, "visible": true, "backgroundColor": "", "fillRule": "nonzero", "paintFirst": "fill", "globalCompositeOperation": "source-over", "skewX": 0, "skewY": 0, "dataTag": "rating", "selectable": true, "evented": true, "lockScalingY": false, "objects": [{"type": "image", "version": "5.3.0", "originX": "left", "originY": "top", "left": -56.07, "top": -15, "width": 1200, "height": 605, "fill": "rgb(0,0,0)", "stroke": null, "strokeWidth": 0, "strokeDashArray": null, "strokeLineCap": "butt", "strokeDashOffset": 0, "strokeLineJoin": "miter", "strokeUniform": false, "strokeMiterLimit": 4, "scaleX": 0.05, "scaleY": 0.05, "angle": 0, "flipX": false, "flipY": false, "opacity": 1, "shadow": null, "visible": true, "backgroundColor": "", "fillRule": "nonzero", "paintFirst": "fill", "globalCompositeOperation": "source-over", "skewX": 0, "skewY": 0, "cropX": 0, "cropY": 0, "dataTag": "rating_logo_img", "selectable": true, "evented": true, "lockScalingY": false, "src": "http://truenas:5000/api/proxy/image?url=https%3A%2F%2Fupload.wikimedia.org%2Fwikipedia%2Fcommons%2Fthumb%2F6%2F69%2FIMDB_Logo_2016.svg%2F1200px-IMDB_Logo_2016.svg.png", "crossOrigin": "anonymous", "filters": []}, {"type": "i-text", "version": "5.3.0", "originX": "left", "originY": "top", "left": 13.44, "top": -17.45, "width": 41.63, "height": 33.9, "fill": "#c98282", "stroke": null, "strokeWidth": 1, "strokeDashArray": null, "strokeLineCap": "butt", "strokeDashOffset": 0, "strokeLineJoin": "miter", "strokeUniform": false, "strokeMiterLimit": 4, "scaleX": 1, "scaleY": 1, "angle": 0, "flipX": false, "flipY": false, "opacity": 1, "shadow": null, "visible": true, "backgroundColor": "", "fillRule": "nonzero", "paintFirst": "fill", "globalCompositeOperation": "source-over", "skewX": 0, "skewY": 0, "fontFamily": "Roboto", "fontWeight": "normal", "fontSize": 30, "text": "7.8", "underline": false, "overline": false, "linethrough": false, "textAlign": "left", "fontStyle": "normal", "lineHeight": 1.16, "textBackgroundColor": "", "charSpacing": 0, "styles": [], "direction": "ltr", "path": null, "pathStartOffset": 0, "pathSide": "left", "pathAlign": "baseline", "dataTag": "rating", "selectable": true, "evented": true, "lockScalingY": false, "editable": false}]}, {"type": "i-text", "version": "5.3.0", "originX": "left", "originY": "top", "left": 1665.07, "top": 492.14, "width": 88.21, "height": 33.9, "fill": "#c98282", "stroke": null, "strokeWidth": 1, "strokeDashArray": null, "strokeLineCap": "butt", "strokeDashOffset": 0, "strokeLineJoin": "miter", "strokeUniform": false, "strokeMiterLimit": 4, "scaleX": 1, "scaleY": 1, "angle": 0, "flipX": false, "flipY": false, "opacity": 1, "shadow": {"color": "rgba(0,0,0,0.8)", "blur": 10, "offsetX": 2, "offsetY": 2, "affectStroke": false, "nonScaling": false}, "visible": true, "backgroundColor": "", "fillRule": "nonzero", "paintFirst": "fill", "globalCompositeOperation": "source-over", "skewX": 0, "skewY": 0, "fontFamily": "Roboto", "fontWeight": "normal", "fontSize": 30, "text": "Drama", "underline": false, "overline": false, "linethrough": false, "textAlign": "left", "fontStyle": "normal", "lineHeight": 1.16, "textBackgroundColor": "", "charSpacing": 0, "styles": [], "direction": "ltr", "path": null, "pathStartOffset": 0, "pathSide": "left", "pathAlign": "baseline", "dataTag": "genres", "selectable": true, "evented": true, "lockScalingY": false, "editable": false}, {"type": "i-text", "version": "5.3.0", "originX": "left", "originY": "top", "left": 1774.28, "top": 492.14, "width": 124.72, "height": 33.9, "fill": "#c98282", "stroke": null, "strokeWidth": 1, "strokeDashArray": null, "strokeLineCap": "butt", "strokeDashOffset": 0, "strokeLineJoin": "miter", "strokeUniform": false, "strokeMiterLimit": 4, "scaleX": 1, "scaleY": 1, "angle": 0, "flipX": false, "flipY": false, "opacity": 1, "shadow": {"color": "rgba(0,0,0,0.8)", "blur": 10, "offsetX": 2, "offsetY": 2, "affectStroke": false, "nonScaling": false}, "visible": true, "backgroundColor": "", "fillRule": "nonzero", "paintFirst": "fill", "globalCompositeOperation": "source-over", "skewX": 0, "skewY": 0, "fontFamily": "Roboto", "fontWeight": "normal", "fontSize": 30, "text": "2h 46min", "underline": false, "overline": false, "linethrough": false, "textAlign": "left", "fontStyle": "normal", "lineHeight": 1.16, "textBackgroundColor": "", "charSpacing": 0, "styles": [], "direction": "ltr", "path": null, "pathStartOffset": 0, "pathSide": "left", "pathAlign": "baseline", "dataTag": "runtime", "selectable": true, "evented": true, "lockScalingY": false, "editable": false}, {"type": "textbox", "version": "5.3.0", "originX": "left", "originY": "top", "left": 1299, "top": 547.04, "width": 600, "height": 83.05, "fill": "white", "stroke": null, "strokeWidth": 1, "strokeDashArray": null, "strokeLineCap": "butt", "strokeDashOffset": 0, "strokeLineJoin": "miter", "strokeUniform": false, "strokeMiterLimit": 4, "scaleX": 1, "scaleY": 1, "angle": 0, "flipX": false, "flipY": false, "opacity": 1, "shadow": {"color": "rgba(0,0,0,0.8)", "blur": 10, "offsetX": 2, "offsetY": 2, "affectStroke": false, "nonScaling": false}, "visible": true, "backgroundColor": "", "fillRule": "nonzero", "paintFirst": "fill", "globalCompositeOperation": "source-over", "skewX": 0, "skewY": 0, "fontFamily": "Roboto", "fontWeight": "normal", "fontSize": 35, "text": "Drogenhandel und Ganggewalt sind in der Stadt Compton im S\u00fcden von LA...", "underline": false, "overline": false, "linethrough": false, "textAlign": "right", "fontStyle": "normal", "lineHeight": 1.1, "textBackgroundColor": "", "charSpacing": 0, "styles": [], "direction": "ltr", "path": null, "pathStartOffset": 0, "pathSide": "left", "pathAlign": "baseline", "minWidth": 20, "splitByGrapheme": false, "dataTag": "overview", "fullMediaText": "Drogenhandel und Ganggewalt sind in der Stadt Compton im S\u00fcden von LA an der Tagesordnung, w\u00e4hrend die Polizei den vielen afroamerikanischen Einwohnern hier h\u00e4ufig mit Rassismus begegnet. Die scheinbar aussichtslose Lage veranlasst Mitte der 80er Jahre schlie\u00dflich f\u00fcnf junge M\u00e4nner dazu, ihren brutalen Alltag mittels Musik zu verarbeiten und so ihre Stimmen gegen die herrschenden Missst\u00e4nde zu erheben. Unter ihren K\u00fcnstlernamen Dr. Dre, Ice Cube, MC Ren, Eazy-E und DJ Yella gr\u00fcnden sie gemeinsam die Hip-Hop-Gruppe N.W.A. Mit harten Beats und ebenso ehrlichen wie kontroversen Texten sorgen sie f\u00fcr gro\u00dfes Aufsehen und ecken vor allem auch bei der Polizei geh\u00f6rig an. Der enorme Erfolg, den sie mit ihrem Album \u201eStraight Outta Compton\u201c feiern k\u00f6nnen, gibt ihnen allerdings Recht. Doch mit dem Ruhm gehen auch zunehmend ernster werdende Differenzen zwischen den Rappern einher, sodass N.W.A so kurz nach dem gro\u00dfen Durchbruch schon wieder auseinanderzubrechen droht.", "selectable": true, "evented": true, "lockScalingY": false, "fixedHeight": 130.4889557855129, "editable": false}, {"type": "i-text", "version": "5.3.0", "originX": "left", "originY": "top", "left": 1569.63, "top": 651.1, "width": 329.37, "height": 33.9, "fill": "#c98282", "stroke": null, "strokeWidth": 1, "strokeDashArray": null, "strokeLineCap": "butt", "strokeDashOffset": 0, "strokeLineJoin": "miter", "strokeUniform": false, "strokeMiterLimit": 4, "scaleX": 1, "scaleY": 1, "angle": 0, "flipX": false, "flipY": false, "opacity": 1, "shadow": {"color": "rgba(0,0,0,0.8)", "blur": 10, "offsetX": 2, "offsetY": 2, "affectStroke": false, "nonScaling": false}, "visible": true, "backgroundColor": "", "fillRule": "nonzero", "paintFirst": "fill", "globalCompositeOperation": "source-over", "skewX": 0, "skewY": 0, "fontFamily": "Roboto", "fontWeight": "normal", "fontSize": 30, "text": "Now available on Jellyfin", "underline": false, "overline": false, "linethrough": false, "textAlign": "right", "fontStyle": "normal", "lineHeight": 1.16, "textBackgroundColor": "", "charSpacing": 0, "styles": [], "direction": "ltr", "path": null, "pathStartOffset": 0, "pathSide": "left", "pathAlign": "baseline", "dataTag": "provider_source", "selectable": true, "evented": true, "lockScalingY": false, "editable": false}, {"type": "image", "version": "5.3.0", "originX": "left", "originY": "top", "left": 0, "top": 0, "width": 1920, "height": 1080, "fill": "rgb(0,0,0)", "stroke": null, "strokeWidth": 0, "strokeDashArray": null, "strokeLineCap": "butt", "strokeDashOffset": 0, "strokeLineJoin": "miter", "strokeUniform": false, "strokeMiterLimit": 4, "scaleX": 1, "scaleY": 1, "angle": 0, "flipX": false, "flipY": false, "opacity": 0.5, "shadow": null, "visible": true, "backgroundColor": "", "fillRule": "nonzero", "paintFirst": "fill", "globalCompositeOperation": "source-over", "skewX": 0, "skewY": 0, "cropX": 0, "cropY": 0, "dataTag": "guide_overlay", "selectable": false, "evented": false, "lockScalingY": false, "src": "http://truenas:5000/api/overlays/image/ec26c288-c32c-4da2-a395-99a7e507f950_1080.png", "crossOrigin": null, "filters": []}, {"type": "image", "version": "5.3.0", "originX": "left", "originY": "top", "left": 1591.76, "top": 161, "width": 531, "height": 536, "fill": "rgb(0,0,0)", "stroke": null, "strokeWidth": 0, "strokeDashArray": null, "strokeLineCap": "butt", "strokeDashOffset": 0, "strokeLineJoin": "miter", "strokeUniform": false, "strokeMiterLimit": 4, "scaleX": 0.58, "scaleY": 0.58, "angle": 0, "flipX": false, "flipY": false, "opacity": 1, "shadow": null, "visible": true, "backgroundColor": "", "fillRule": "nonzero", "paintFirst": "fill", "globalCompositeOperation": "source-over", "skewX": 0, "skewY": 0, "cropX": 0, "cropY": 0, "dataTag": "title", "selectable": true, "evented": true, "lockScalingY": false, "src": "http://truenas:5000/api/proxy/image?url=http%3A%2F%2F192.168.178.92%3A30013%2FItems%2Fef573e398247f1814684eb9e637ab615%2FImages%2FLogo%3Fapi_key%3Db00ae14a7c3249b2b154f22f75e1ecfd&raw=true", "crossOrigin": "anonymous", "filters": []}, {"type": "image", "version": "5.3.0", "originX": "left", "originY": "top", "left": 1610.17, "top": 492.14, "width": 768, "height": 768, "fill": "rgb(0,0,0)", "stroke": null, "strokeWidth": 0, "strokeDashArray": null, "strokeLineCap": "butt", "strokeDashOffset": 0, "strokeLineJoin": "miter", "strokeUniform": false, "strokeMiterLimit": 4, "scaleX": 0.05, "scaleY": 0.05, "angle": 0, "flipX": false, "flipY": false, "opacity": 1, "shadow": null, "visible": true, "backgroundColor": "", "fillRule": "nonzero", "paintFirst": "fill", "globalCompositeOperation": "source-over", "skewX": 0, "skewY": 0, "cropX": 0, "cropY": 0, "dataTag": "certification", "selectable": true, "evented": true, "lockScalingY": false, "matchHeight": true, "src": "http://truenas:5000/api/certification/FSK_12.svg", "crossOrigin": "anonymous", "filters": []}], "background": "#1c1c1c", "metadata": {"title": "Straight Outta Compton", "year": 2015, "officialRating": "FSK-12", "communityRating": 7.782, "genres": "Drama, Musik, Historie", "overview": "Drogenhandel und Ganggewalt sind in der Stadt Compton im S\u00fcden von LA an der Tagesordnung, w\u00e4hrend die Polizei den vielen afroamerikanischen Einwohnern hier h\u00e4ufig mit Rassismus begegnet. Die scheinbar aussichtslose Lage veranlasst Mitte der 80er Jahre schlie\u00dflich f\u00fcnf junge M\u00e4nner dazu, ihren brutalen Alltag mittels Musik zu verarbeiten und so ihre Stimmen gegen die herrschenden Missst\u00e4nde zu erheben. Unter ihren K\u00fcnstlernamen Dr. Dre, Ice Cube, MC Ren, Eazy-E und DJ Yella gr\u00fcnden sie gemeinsam die Hip-Hop-Gruppe N.W.A. Mit harten Beats und ebenso ehrlichen wie kontroversen Texten sorgen sie f\u00fcr gro\u00dfes Aufsehen und ecken vor allem auch bei der Polizei geh\u00f6rig an. Der enorme Erfolg, den sie mit ihrem Album \u201eStraight Outta Compton\u201c feiern k\u00f6nnen, gibt ihnen allerdings Recht. Doch mit dem Ruhm gehen auch zunehmend ernster werdende Differenzen zwischen den Rappern einher, sodass N.W.A so kurz nach dem gro\u00dfen Durchbruch schon wieder auseinanderzubrechen droht.", "action_url": "jellyfin://items/ef573e398247f1814684eb9e637ab615", "provider_ids": {"Imdb": "tt1398426", "Tmdb": "277216", "TmdbCollection": "277216", "wikidata": "Q18154625"}, "studios": [], "tags": [], "source": "Jellyfin"}, "action_url": "jellyfin://items/ef573e398247f1814684eb9e637ab615"}